{
	"textures": [
		{
			"image": "foe-spritesheet.png",
			"format": "RGBA8888",
			"size": {
				"w": 750,
				"h": 80
			},
			"scale": 1,
			"frames": [
				{
					"filename": "foe1-1.png",
					"rotated": false,
					"trimmed": false,
					"sourceSize": {
						"w": 75,
						"h": 80
					},
					"spriteSourceSize": {
						"x": 0,
						"y": 0,
						"w": 75,
						"h": 80
					},
					"frame": {
						"x": 0,
						"y": 0,
						"w": 75,
						"h": 80
					}
				},
				{
					"filename": "foe1-2.png",
					"rotated": false,
					"trimmed": false,
					"sourceSize": {
						"w": 75,
						"h": 80
					},
					"spriteSourceSize": {
						"x": 0,
						"y": 0,
						"w": 75,
						"h": 80
					},
					"frame": {
						"x": 75,
						"y": 0,
						"w": 75,
						"h": 80
					}
				},
				{
					"filename": "gegner-1.png",
					"rotated": false,
					"trimmed": false,
					"sourceSize": {
						"w": 75,
						"h": 80
					},
					"spriteSourceSize": {
						"x": 0,
						"y": 0,
						"w": 75,
						"h": 80
					},
					"frame": {
						"x": 150,
						"y": 0,
						"w": 75,
						"h": 80
					}
				},
				{
					"filename": "gegner-2.png",
					"rotated": false,
					"trimmed": false,
					"sourceSize": {
						"w": 75,
						"h": 80
					},
					"spriteSourceSize": {
						"x": 0,
						"y": 0,
						"w": 75,
						"h": 80
					},
					"frame": {
						"x": 225,
						"y": 0,
						"w": 75,
						"h": 80
					}
				},
				{
					"filename": "gegner-3.png",
					"rotated": false,
					"trimmed": false,
					"sourceSize": {
						"w": 75,
						"h": 80
					},
					"spriteSourceSize": {
						"x": 0,
						"y": 0,
						"w": 75,
						"h": 80
					},
					"frame": {
						"x": 300,
						"y": 0,
						"w": 75,
						"h": 80
					}
				},
				{
					"filename": "gegner-4.png",
					"rotated": false,
					"trimmed": false,
					"sourceSize": {
						"w": 75,
						"h": 80
					},
					"spriteSourceSize": {
						"x": 0,
						"y": 0,
						"w": 75,
						"h": 80
					},
					"frame": {
						"x": 375,
						"y": 0,
						"w": 75,
						"h": 80
					}
				},
				{
					"filename": "gegner-5.png",
					"rotated": false,
					"trimmed": false,
					"sourceSize": {
						"w": 75,
						"h": 80
					},
					"spriteSourceSize": {
						"x": 0,
						"y": 0,
						"w": 75,
						"h": 80
					},
					"frame": {
						"x": 450,
						"y": 0,
						"w": 75,
						"h": 80
					}
				},
				{
					"filename": "gegner-6.png",
					"rotated": false,
					"trimmed": false,
					"sourceSize": {
						"w": 75,
						"h": 80
					},
					"spriteSourceSize": {
						"x": 0,
						"y": 0,
						"w": 75,
						"h": 80
					},
					"frame": {
						"x": 525,
						"y": 0,
						"w": 75,
						"h": 80
					}
				},
				{
					"filename": "gegner-7.png",
					"rotated": false,
					"trimmed": false,
					"sourceSize": {
						"w": 75,
						"h": 80
					},
					"spriteSourceSize": {
						"x": 0,
						"y": 0,
						"w": 75,
						"h": 80
					},
					"frame": {
						"x": 600,
						"y": 0,
						"w": 75,
						"h": 80
					}
				},
				{
					"filename": "gegner-8.png",
					"rotated": false,
					"trimmed": false,
					"sourceSize": {
						"w": 75,
						"h": 80
					},
					"spriteSourceSize": {
						"x": 0,
						"y": 0,
						"w": 75,
						"h": 80
					},
					"frame": {
						"x": 675,
						"y": 0,
						"w": 75,
						"h": 80
					}
				}
			]
		}
	],
	"meta": {
		"app": "https://www.codeandweb.com/texturepacker",
		"version": "3.0",
		"smartupdate": "$TexturePacker:SmartUpdate:c878b2652f5d92ab60d12922380afcf5:cb070705e3a8dd7273a6af4c7c37f516:52b67abe975220280b2958de881df67f$"
	}
}
